nocobase_api_sdk/__init__.py
nocobase_api_sdk/client.py
nocobase_api_sdk/getter_filter.py
nocobase_api_sdk/py.typed
nocobase_api_sdk/result.py
nocobase_api_sdk-2.0.0.dist-info/WHEEL
nocobase_api_sdk-2.0.0.dist-info/METADATA
nocobase_api_sdk-2.0.0.dist-info/RECORD
