Metadata-Version: 2.3
Name: nocobase-api-sdk
Version: 2.0.0
Summary: NocoBase API SDK
Author: Martian Bugs
Requires-Dist: requests>=2.32.4
Requires-Python: >=3.12
